alignfaces/__init__.py
alignfaces/aperture_tools.py
alignfaces/contrast_tools.py
alignfaces/contrast_tools_.py
alignfaces/face_landmarks.py
alignfaces/make_aligned_faces.py
alignfaces/make_aligned_faces_.py
alignfaces/make_files.py
alignfaces/make_files_.py
alignfaces/make_files_OLD.py
alignfaces/phase_cong_3.py
alignfaces/plot_tools.py
alignfaces/procrustes_tools.py
alignfaces/warp_tools.py
alignfaces/data/shape_predictor_68_face_landmarks.dat
alignfaces/tests/__init__.py
alignfaces/tests/_test_pawarp.py
alignfaces/tests/test_procrustes_tools.py
alignfaces/tests/test_warp_tools.py
alignfaces/tests/R/align_reference.csv
alignfaces/tests/R/align_shapes.csv
alignfaces/tests/R/input_shapes.csv
alignfaces-1.0.1.dist-info/licenses/LICENSE.txt
alignfaces-1.0.1.dist-info/METADATA
alignfaces-1.0.1.dist-info/WHEEL
alignfaces-1.0.1.dist-info/top_level.txt
alignfaces-1.0.1.dist-info/RECORD
