Metadata-Version: 2.4
Name: alignfaces
Version: 1.0.1
Summary: Automatically align and warp face images
Author-email: Carl Michael Gaspar <carl.michael.gaspar@icloud.com>, "Oliver G.B. Garrod" <oliver.garrod@fabdata.io>
License: Apache-2.0
Keywords: face-alignment,face-morphing,psychophysics,psychology-experiments
Requires-Python: >=3.9
License-File: LICENSE.txt
Requires-Dist: dlib
Requires-Dist: scikit-image
Dynamic: license-file
